NotipyDesktop/NotipyDesktop.py
NotipyDesktop/__init__.py
NotipyDesktop-10.0.0.dist-info/LICENSE
NotipyDesktop-10.0.0.dist-info/METADATA
NotipyDesktop-10.0.0.dist-info/WHEEL
NotipyDesktop-10.0.0.dist-info/top_level.txt
NotipyDesktop-10.0.0.dist-info/RECORD
