Metadata-Version: 2.1
Name: NotipyDesktop
Version: 10.0.0
Summary: A simple Python notification library using libnotify.
Home-page: https://github.com/Michdo93/NotipyDesktop
Author: Michael Christian Dörflinger
Author-email: michaeldoerflinger93@gmail.com
Classifier: Programming Language :: Python :: 3
Classifier: License :: OSI Approved :: MIT License
Classifier: Operating System :: OS Independent
Requires-Python: >=3.6
License-File: LICENSE
Requires-Dist: PyGObject
